data_app_example/__init__.py
data_app_example/hello_world.py
data_app_example-0.0.1.dist-info/METADATA
data_app_example-0.0.1.dist-info/WHEEL
data_app_example-0.0.1.dist-info/top_level.txt
data_app_example-0.0.1.dist-info/RECORD
