Metadata-Version: 2.1
Name: data-app-example
Version: 0.0.1
Summary: this an simplr project for demo
Author: data_app1
Author-email: data_app1@mail.com
License: UNKNOWN
Platform: UNKNOWN
